[
    {
        "name": "Nước tương thượng hạng Nam Dương",
        "price": "109,000",
        "unit": "Lốc",
        "url": "https://online.mmvietnam.com/san-pham/mm-an-phu/nuoc-tuong-thuong-hang-nam-duong-loc-6-chai-210ml-836673/",
        "category": "dau an gia vi nuoc cham",
        "image": "https://storage.googleapis.com/mm-online-bucket/ecommerce-website/uploads/media/420823-300x300.jpg",
        "quantity": "lốc 6 chai",
        "domain_url": "https://online.mmvietnam.com/"
    },
    {
        "name": "Dầu ăn Happy Price",
        "price": "733,000",
        "unit": "Thùng",
        "url": "https://online.mmvietnam.com/san-pham/mm-an-phu/dau-an-happy-price-thung-4-binh-5-lit-binh-830450/",
        "category": "dau an gia vi nuoc cham",
        "image": "https://storage.googleapis.com/mm-online-bucket/ecommerce-website/uploads/media/324525-300x300.jpg",
        "quantity": "thùng 4 bình",
        "domain_url": "https://online.mmvietnam.com/"
    },
    {
        "name": "Dầu ăn Neptune Gold",
        "price": "579,000",
        "unit": "Thùng",
        "url": "https://online.mmvietnam.com/san-pham/mm-an-phu/dau-an-neptune-gold-thung-6-chai-2-lit-830132/",
        "category": "dau an gia vi nuoc cham",
        "image": "data:image/svg+xml;charset=utf-8,%3Csvg xmlns%3D'http%3A%2F%2Fwww.w3.org%2F2000%2Fsvg' viewBox%3D'0 0 300 300'%2F%3E",
        "quantity": "thùng 6 chai",
        "domain_url": "https://online.mmvietnam.com/"
    },
    {
        "name": "Bột ngọt Vedan (LM)",
        "price": "1,329,000",
        "unit": "Thùng",
        "url": "https://online.mmvietnam.com/san-pham/mm-an-phu/bot-ngot-vedan-thung-40-goi-x-450g-830144/",
        "category": "dau an gia vi nuoc cham",
        "image": "data:image/svg+xml;charset=utf-8,%3Csvg xmlns%3D'http%3A%2F%2Fwww.w3.org%2F2000%2Fsvg' viewBox%3D'0 0 300 300'%2F%3E",
        "quantity": "thùng 40 gói",
        "domain_url": "https://online.mmvietnam.com/"
    },
    {
        "name": "Dầu ăn Tường An",
        "price": "1,142,000",
        "unit": "Thùng",
        "url": "https://online.mmvietnam.com/san-pham/mm-an-phu/dau-an-tuong-an-cooking-oil-thung-4-binh-x-5-lit-830153/",
        "category": "dau an gia vi nuoc cham",
        "image": "data:image/svg+xml;charset=utf-8,%3Csvg xmlns%3D'http%3A%2F%2Fwww.w3.org%2F2000%2Fsvg' viewBox%3D'0 0 300 300'%2F%3E",
        "quantity": "thùng 4 bình",
        "domain_url": "https://online.mmvietnam.com/"
    },
    {
        "name": "Dầu đậu nành Meizan",
        "price": "1,125,000",
        "unit": "Thùng",
        "url": "https://online.mmvietnam.com/san-pham/mm-an-phu/dau-dau-nanh-meizan-100-nguyen-chat-thung-4-binh-x-5-lit-830160/",
        "category": "dau an gia vi nuoc cham",
        "image": "data:image/svg+xml;charset=utf-8,%3Csvg xmlns%3D'http%3A%2F%2Fwww.w3.org%2F2000%2Fsvg' viewBox%3D'0 0 300 300'%2F%3E",
        "quantity": "thùng 4 bình",
        "domain_url": "https://online.mmvietnam.com/"
    },
    {
        "name": "Nước chấm Nam Ngư siêu tiết kiệm",
        "price": "239,000",
        "unit": "Thùng",
        "url": "https://online.mmvietnam.com/san-pham/mm-an-phu/nuoc-cham-nam-ngu-sieu-tiet-kiem-thung-4-binh-4-8-lit-binh-830164/",
        "category": "dau an gia vi nuoc cham",
        "image": "data:image/svg+xml;charset=utf-8,%3Csvg xmlns%3D'http%3A%2F%2Fwww.w3.org%2F2000%2Fsvg' viewBox%3D'0 0 300 300'%2F%3E",
        "quantity": "thùng 4 bình",
        "domain_url": "https://online.mmvietnam.com/"
    },
    {
        "name": "Hạt nêm Maggi nấm hương",
        "price": "189,000",
        "unit": "Gói",
        "url": "https://online.mmvietnam.com/san-pham/mm-an-phu/hat-nem-maggi-nam-huong-2kg-830002/",
        "category": "dau an gia vi nuoc cham",
        "image": "data:image/svg+xml;charset=utf-8,%3Csvg xmlns%3D'http%3A%2F%2Fwww.w3.org%2F2000%2Fsvg' viewBox%3D'0 0 300 300'%2F%3E",
        "quantity": "2kg",
        "domain_url": "https://online.mmvietnam.com/"
    },
    {
        "name": "Hạt nêm Neptune tam bảo vị nấm",
        "price": "36,600",
        "unit": "Gói",
        "url": "https://online.mmvietnam.com/san-pham/mm-an-phu/mua-2-tinh-tien-1-hat-nem-neptune-tam-bao-vi-nam-380g-824482/",
        "category": "dau an gia vi nuoc cham",
        "image": "data:image/svg+xml;charset=utf-8,%3Csvg xmlns%3D'http%3A%2F%2Fwww.w3.org%2F2000%2Fsvg' viewBox%3D'0 0 300 300'%2F%3E",
        "quantity": "380g",
        "domain_url": "https://online.mmvietnam.com/"
    },
    {
        "name": "Hạt nêm Knorr chay nấm hương organic",
        "price": "63,000",
        "unit": "Gói",
        "url": "https://online.mmvietnam.com/san-pham/mm-an-phu/hat-nem-knorr-chay-nam-huong-organic-goi-800g-818290/",
        "category": "dau an gia vi nuoc cham",
        "image": "data:image/svg+xml;charset=utf-8,%3Csvg xmlns%3D'http%3A%2F%2Fwww.w3.org%2F2000%2Fsvg' viewBox%3D'0 0 300 300'%2F%3E",
        "quantity": "gói 800g",
        "domain_url": "https://online.mmvietnam.com/"
    },
    {
        "name": "Nước mắm Knorr hảo hạng",
        "price": "98,000",
        "unit": "Chai",
        "url": "https://online.mmvietnam.com/san-pham/mm-an-phu/nuoc-mam-knorr-cao-cap-43-do-dam-chai-thuy-tinh-500ml-818698/",
        "category": "dau an gia vi nuoc cham",
        "image": "data:image/svg+xml;charset=utf-8,%3Csvg xmlns%3D'http%3A%2F%2Fwww.w3.org%2F2000%2Fsvg' viewBox%3D'0 0 300 300'%2F%3E",
        "quantity": "500ml",
        "domain_url": "https://online.mmvietnam.com/"
    },
    {
        "name": "Tương cà Happy Price",
        "price": "110,000",
        "unit": "Bịch",
        "url": "https://online.mmvietnam.com/san-pham/mm-an-phu/tuong-ca-happy-price-bich-200-goi-10g-817470/",
        "category": "dau an gia vi nuoc cham",
        "image": "data:image/svg+xml;charset=utf-8,%3Csvg xmlns%3D'http%3A%2F%2Fwww.w3.org%2F2000%2Fsvg' viewBox%3D'0 0 300 300'%2F%3E",
        "quantity": "bịch 200 gói",
        "domain_url": "https://online.mmvietnam.com/"
    }
]