[
    {
        "name": "Chả giò da xốp Hoa Mai Cầu Tre nhân thịt",
        "price": "61,000",
        "unit": "Gói",
        "url": "https://online.mmvietnam.com/san-pham/mm-an-phu/cha-gio-da-xop-hoa-mai-cau-tre-nhan-thit-heo-500g-10/",
        "category": "thuc pham dong lanh",
        "image": "data:image/svg+xml;charset=utf-8,%3Csvg xmlns%3D'http%3A%2F%2Fwww.w3.org%2F2000%2Fsvg' viewBox%3D'0 0 300 300'%2F%3E",
        "quantity": "500g",
        "domain_url": "https://online.mmvietnam.com/"
    },
    {
        "name": "Cá viên nhân trứng cá Tobiko",
        "price": "66,000",
        "unit": "Gói",
        "url": "https://online.mmvietnam.com/san-pham/mm-an-phu/ca-vien-nhan-trung-ca-tobiko-240g-12/",
        "category": "thuc pham dong lanh",
        "image": "data:image/svg+xml;charset=utf-8,%3Csvg xmlns%3D'http%3A%2F%2Fwww.w3.org%2F2000%2Fsvg' viewBox%3D'0 0 300 300'%2F%3E",
        "quantity": "240g",
        "domain_url": "https://online.mmvietnam.com/"
    },
    {
        "name": "Cá viên nhân Mayonaise rau củ",
        "price": "79,000",
        "unit": "Gói",
        "url": "https://online.mmvietnam.com/san-pham/mm-an-phu/ca-vien-nhan-mayonaise-rau-cu-500g-16/",
        "category": "thuc pham dong lanh",
        "image": "data:image/svg+xml;charset=utf-8,%3Csvg xmlns%3D'http%3A%2F%2Fwww.w3.org%2F2000%2Fsvg' viewBox%3D'0 0 300 300'%2F%3E",
        "quantity": "500g",
        "domain_url": "https://online.mmvietnam.com/"
    },
    {
        "name": "Tôm cuộn khoai môn We Are Fresh",
        "price": "94,000",
        "unit": "Gói",
        "url": "https://online.mmvietnam.com/san-pham/mm-an-phu/tom-cuon-khoai-mon-big-meal-300g-10/",
        "category": "thuc pham dong lanh",
        "image": "data:image/svg+xml;charset=utf-8,%3Csvg xmlns%3D'http%3A%2F%2Fwww.w3.org%2F2000%2Fsvg' viewBox%3D'0 0 300 300'%2F%3E",
        "quantity": "300g",
        "domain_url": "https://online.mmvietnam.com/"
    },
    {
        "name": "Cua đồng xay đông lạnh TLE",
        "price": "38,000",
        "unit": "Gói",
        "url": "https://online.mmvietnam.com/san-pham/mm-an-phu/cua-dong-xay-dong-lanh-tl-250g-11/",
        "category": "thuc pham dong lanh",
        "image": "data:image/svg+xml;charset=utf-8,%3Csvg xmlns%3D'http%3A%2F%2Fwww.w3.org%2F2000%2Fsvg' viewBox%3D'0 0 300 300'%2F%3E",
        "quantity": "250g",
        "domain_url": "https://online.mmvietnam.com/"
    },
    {
        "name": "Nạc vai trâu 65 đông lạnh We Are Fresh xuất xứ Ấn Độ",
        "price": "149,900",
        "unit": "Ký",
        "url": "https://online.mmvietnam.com/san-pham/mm-an-phu/nac-vai-trau-65-dong-lanh-xuat-xu-an-do/",
        "category": "thuc pham dong lanh",
        "image": "data:image/svg+xml;charset=utf-8,%3Csvg xmlns%3D'http%3A%2F%2Fwww.w3.org%2F2000%2Fsvg' viewBox%3D'0 0 300 300'%2F%3E",
        "quantity": "250g",
        "domain_url": "https://online.mmvietnam.com/"
    },
    {
        "name": "Mực lá đại dương đông lạnh",
        "price": "259,000",
        "unit": "Ký",
        "url": "https://online.mmvietnam.com/san-pham/mm-an-phu/muc-la-dai-duong-nhap-khau-dong-lanh-3kg-11/",
        "category": "thuc pham dong lanh",
        "image": "data:image/svg+xml;charset=utf-8,%3Csvg xmlns%3D'http%3A%2F%2Fwww.w3.org%2F2000%2Fsvg' viewBox%3D'0 0 300 300'%2F%3E",
        "quantity": "3kg trở lên",
        "domain_url": "https://online.mmvietnam.com/"
    },
    {
        "name": "Đậu nành đông lạnh MM",
        "price": "86,000",
        "unit": "Gói",
        "url": "https://online.mmvietnam.com/san-pham/mm-an-phu/dau-nanh-dong-lanh-mm-1kg-2/",
        "category": "thuc pham dong lanh",
        "image": "data:image/svg+xml;charset=utf-8,%3Csvg xmlns%3D'http%3A%2F%2Fwww.w3.org%2F2000%2Fsvg' viewBox%3D'0 0 300 300'%2F%3E",
        "quantity": "1kg",
        "domain_url": "https://online.mmvietnam.com/"
    },
    {
        "name": "Phúc bồn tử đông lạnh MM",
        "price": "169,000",
        "unit": "Gói",
        "url": "https://online.mmvietnam.com/san-pham/mm-an-phu/phuc-bon-tu-dong-lanh-mm-1kg-2/",
        "category": "thuc pham dong lanh",
        "image": "data:image/svg+xml;charset=utf-8,%3Csvg xmlns%3D'http%3A%2F%2Fwww.w3.org%2F2000%2Fsvg' viewBox%3D'0 0 300 300'%2F%3E",
        "quantity": "1kg",
        "domain_url": "https://online.mmvietnam.com/"
    },
    {
        "name": "Bông cải xanh đông lạnh MM",
        "price": "86,000",
        "unit": "Gói",
        "url": "https://online.mmvietnam.com/san-pham/mm-an-phu/bong-cai-xanh-dong-lanh-mm-1kg-2/",
        "category": "thuc pham dong lanh",
        "image": "data:image/svg+xml;charset=utf-8,%3Csvg xmlns%3D'http%3A%2F%2Fwww.w3.org%2F2000%2Fsvg' viewBox%3D'0 0 300 300'%2F%3E",
        "quantity": "1kg",
        "domain_url": "https://online.mmvietnam.com/"
    }
]