[
    {
        "name": "Cá dứa đông lạnh OCOP",
        "price": "155,000",
        "unit": "Gói",
        "url": "https://online.mmvietnam.com/san-pham/mm-an-phu/ca-dua-dong-lanh-ocop-500g-892888/",
        "category": "thuc pham tuoi song",
        "image": "https://storage.googleapis.com/mm-online-bucket/ecommerce-website/uploads/media/410511-300x300.jpg",
        "quantity": "500g",
        "domain_url": "https://online.mmvietnam.com/"
    },
    {
        "name": "Cá dứa fillet đông lạnh có da",
        "price": "79,000",
        "unit": "Gói",
        "url": "https://online.mmvietnam.com/san-pham/mm-an-phu/ca-dua-fillet-dong-lanh-co-da-500g-892914/",
        "category": "thuc pham tuoi song",
        "image": "https://storage.googleapis.com/mm-online-bucket/ecommerce-website/uploads/media/412984-300x300.jpg",
        "quantity": "500g",
        "domain_url": "https://online.mmvietnam.com/"
    },
    {
        "name": "Cá trích ép trứng đông lạnh xuất xứ Nhật",
        "price": "1,375,000",
        "unit": "Gói",
        "url": "https://online.mmvietnam.com/san-pham/mm-an-phu/ca-trich-ep-trung-dong-lanh-xuat-xu-nhat-892945/",
        "category": "thuc pham tuoi song",
        "image": "data:image/svg+xml;charset=utf-8,%3Csvg xmlns%3D'http%3A%2F%2Fwww.w3.org%2F2000%2Fsvg' viewBox%3D'0 0 300 300'%2F%3E",
        "quantity": "500g",
        "domain_url": "https://online.mmvietnam.com/"
    },
    {
        "name": "Cồi sò điệp Nhật đông lạnh",
        "price": "969,000",
        "unit": "Gói",
        "url": "https://online.mmvietnam.com/san-pham/mm-an-phu/coi-so-diep-nhat-dong-lanh-1kg-892948/",
        "category": "thuc pham tuoi song",
        "image": "data:image/svg+xml;charset=utf-8,%3Csvg xmlns%3D'http%3A%2F%2Fwww.w3.org%2F2000%2Fsvg' viewBox%3D'0 0 300 300'%2F%3E",
        "quantity": "1kg",
        "domain_url": "https://online.mmvietnam.com/"
    },
    {
        "name": "Đùi ếch đông lạnh Top Meal",
        "price": "115,000",
        "unit": "Gói",
        "url": "https://online.mmvietnam.com/san-pham/mm-an-phu/dui-ech-dong-lanh-top-meal-500g-892983/",
        "category": "thuc pham tuoi song",
        "image": "data:image/svg+xml;charset=utf-8,%3Csvg xmlns%3D'http%3A%2F%2Fwww.w3.org%2F2000%2Fsvg' viewBox%3D'0 0 300 300'%2F%3E",
        "quantity": "500g",
        "domain_url": "https://online.mmvietnam.com/"
    },
    {
        "name": "Hàu nướng phô mai",
        "price": "80,000",
        "unit": "Gói",
        "url": "https://online.mmvietnam.com/san-pham/mm-an-phu/hau-nuong-pho-mai-300g-893007/",
        "category": "thuc pham tuoi song",
        "image": "data:image/svg+xml;charset=utf-8,%3Csvg xmlns%3D'http%3A%2F%2Fwww.w3.org%2F2000%2Fsvg' viewBox%3D'0 0 300 300'%2F%3E",
        "quantity": "300g",
        "domain_url": "https://online.mmvietnam.com/"
    },
    {
        "name": "Khô cá đuối 1 nắng đông lạnh",
        "price": "125,000",
        "unit": "Gói",
        "url": "https://online.mmvietnam.com/san-pham/mm-an-phu/kho-ca-duoi-1-nang-dong-lanh-500g-893014/",
        "category": "thuc pham tuoi song",
        "image": "data:image/svg+xml;charset=utf-8,%3Csvg xmlns%3D'http%3A%2F%2Fwww.w3.org%2F2000%2Fsvg' viewBox%3D'0 0 300 300'%2F%3E",
        "quantity": "500g",
        "domain_url": "https://online.mmvietnam.com/"
    },
    {
        "name": "Khô cá rô phi 1 nắng đông lạnh",
        "price": "99,000",
        "unit": "Gói",
        "url": "https://online.mmvietnam.com/san-pham/mm-an-phu/kho-ca-ro-phi-1-nang-dong-lanh-500g-893032/",
        "category": "thuc pham tuoi song",
        "image": "data:image/svg+xml;charset=utf-8,%3Csvg xmlns%3D'http%3A%2F%2Fwww.w3.org%2F2000%2Fsvg' viewBox%3D'0 0 300 300'%2F%3E",
        "quantity": "500g",
        "domain_url": "https://online.mmvietnam.com/"
    },
    {
        "name": "Khô cá sặc 1 nắng đông lạnh",
        "price": "175,000",
        "unit": "Gói",
        "url": "https://online.mmvietnam.com/san-pham/mm-an-phu/kho-ca-sac-1-nang-dong-lanh-500g-893060/",
        "category": "thuc pham tuoi song",
        "image": "data:image/svg+xml;charset=utf-8,%3Csvg xmlns%3D'http%3A%2F%2Fwww.w3.org%2F2000%2Fsvg' viewBox%3D'0 0 300 300'%2F%3E",
        "quantity": "500g",
        "domain_url": "https://online.mmvietnam.com/"
    },
    {
        "name": "Mực 1 nắng đông lạnh",
        "price": "600,000",
        "unit": "Gói",
        "url": "https://online.mmvietnam.com/san-pham/mm-an-phu/muc-1-nang-dong-lanh-1kg-893090/",
        "category": "thuc pham tuoi song",
        "image": "data:image/svg+xml;charset=utf-8,%3Csvg xmlns%3D'http%3A%2F%2Fwww.w3.org%2F2000%2Fsvg' viewBox%3D'0 0 300 300'%2F%3E",
        "quantity": "1kg",
        "domain_url": "https://online.mmvietnam.com/"
    },
    {
        "name": "Mực cắt hoa đông lạnh",
        "price": "70,000",
        "unit": "Gói",
        "url": "https://online.mmvietnam.com/san-pham/mm-an-phu/muc-cat-hoa-dong-lanh-600g-893100/",
        "category": "thuc pham tuoi song",
        "image": "data:image/svg+xml;charset=utf-8,%3Csvg xmlns%3D'http%3A%2F%2Fwww.w3.org%2F2000%2Fsvg' viewBox%3D'0 0 300 300'%2F%3E",
        "quantity": "600g",
        "domain_url": "https://online.mmvietnam.com/"
    },
    {
        "name": "Mực ống cắt khoanh",
        "price": "190,000",
        "unit": "Gói",
        "url": "https://online.mmvietnam.com/san-pham/mm-an-phu/muc-ong-cat-khoanh-900g-893138/",
        "category": "thuc pham tuoi song",
        "image": "data:image/svg+xml;charset=utf-8,%3Csvg xmlns%3D'http%3A%2F%2Fwww.w3.org%2F2000%2Fsvg' viewBox%3D'0 0 300 300'%2F%3E",
        "quantity": "900g",
        "domain_url": "https://online.mmvietnam.com/"
    }
]