[
    {
        "name": "Kẹo dẻo Thái Haribo Worms",
        "price": "23,000",
        "unit": "Gói",
        "url": "https://online.mmvietnam.com/san-pham/mm-an-phu/keo-deo-thai-haribo-worms-80g-474409/",
        "category": "banh keo cac loai",
        "image": "https://storage.googleapis.com/mm-online-bucket/ecommerce-website/uploads/media/357463-300x300.jpg",
        "quantity": "80g",
        "domain_url": "https://online.mmvietnam.com/"
    },
    {
        "name": "Kẹo dẻo Thái Haribo Fruity Basket",
        "price": "23,000",
        "unit": "Gói",
        "url": "https://online.mmvietnam.com/san-pham/mm-an-phu/keo-deo-thai-haribo-fruity-basket-80g-474429/",
        "category": "banh keo cac loai",
        "image": "https://storage.googleapis.com/mm-online-bucket/ecommerce-website/uploads/media/357464-300x300.jpg",
        "quantity": "80g",
        "domain_url": "https://online.mmvietnam.com/"
    },
    {
        "name": "Kẹo dẻo Thái Haribo Happy Cola",
        "price": "23,000",
        "unit": "Gói",
        "url": "https://online.mmvietnam.com/san-pham/mm-an-phu/keo-deo-thai-haribo-happy-cola-80g-474449/",
        "category": "banh keo cac loai",
        "image": "data:image/svg+xml;charset=utf-8,%3Csvg xmlns%3D'http%3A%2F%2Fwww.w3.org%2F2000%2Fsvg' viewBox%3D'0 0 300 300'%2F%3E",
        "quantity": "80g",
        "domain_url": "https://online.mmvietnam.com/"
    },
    {
        "name": "Bánh que Pocky Glico vị kem bánh quy",
        "price": "16,000",
        "unit": "Hộp",
        "url": "https://online.mmvietnam.com/san-pham/mm-an-phu/banh-que-pocky-glico-vi-kem-banh-quy-40g-474466/",
        "category": "banh keo cac loai",
        "image": "data:image/svg+xml;charset=utf-8,%3Csvg xmlns%3D'http%3A%2F%2Fwww.w3.org%2F2000%2Fsvg' viewBox%3D'0 0 300 300'%2F%3E",
        "quantity": "40g",
        "domain_url": "https://online.mmvietnam.com/"
    },
    {
        "name": "Bánh que Pocky Glico vị trà xanh matcha",
        "price": "16,000",
        "unit": "Hộp",
        "url": "https://online.mmvietnam.com/san-pham/mm-an-phu/banh-que-pocky-glico-vi-tra-xanh-matcha-35g-474503/",
        "category": "banh keo cac loai",
        "image": "data:image/svg+xml;charset=utf-8,%3Csvg xmlns%3D'http%3A%2F%2Fwww.w3.org%2F2000%2Fsvg' viewBox%3D'0 0 300 300'%2F%3E",
        "quantity": "35g",
        "domain_url": "https://online.mmvietnam.com/"
    },
    {
        "name": "Bánh Marine Boy Orion vị gà nướng",
        "price": "11,800",
        "unit": "Hộp",
        "url": "https://online.mmvietnam.com/san-pham/mm-an-phu/banh-marine-boy-orion-vi-ga-nuong-35g-473417/",
        "category": "banh keo cac loai",
        "image": "data:image/svg+xml;charset=utf-8,%3Csvg xmlns%3D'http%3A%2F%2Fwww.w3.org%2F2000%2Fsvg' viewBox%3D'0 0 300 300'%2F%3E",
        "quantity": "35g",
        "domain_url": "https://online.mmvietnam.com/"
    },
    {
        "name": "Bánh Marine Boy Orion vị tôm nướng",
        "price": "11,800",
        "unit": "Hộp",
        "url": "https://online.mmvietnam.com/san-pham/mm-an-phu/banh-marine-boy-orion-vi-tom-nuong-35g-472240/",
        "category": "banh keo cac loai",
        "image": "data:image/svg+xml;charset=utf-8,%3Csvg xmlns%3D'http%3A%2F%2Fwww.w3.org%2F2000%2Fsvg' viewBox%3D'0 0 300 300'%2F%3E",
        "quantity": "35g/32g",
        "domain_url": "https://online.mmvietnam.com/"
    },
    {
        "name": "Bánh Marine Boy Orion vị rong biển",
        "price": "11,800",
        "unit": "Hộp",
        "url": "https://online.mmvietnam.com/san-pham/mm-an-phu/banh-marine-boy-orion-vi-rong-bien-35g-472261/",
        "category": "banh keo cac loai",
        "image": "data:image/svg+xml;charset=utf-8,%3Csvg xmlns%3D'http%3A%2F%2Fwww.w3.org%2F2000%2Fsvg' viewBox%3D'0 0 300 300'%2F%3E",
        "quantity": "35g/32g",
        "domain_url": "https://online.mmvietnam.com/"
    },
    {
        "name": "Bánh Jungle Boy T-Rex Orion vị sườn bò sốt cam",
        "price": "11,800",
        "unit": "Hộp",
        "url": "https://online.mmvietnam.com/san-pham/mm-an-phu/banh-jungle-boy-orion-vi-suon-bo-sot-cam-35g-471879/",
        "category": "banh keo cac loai",
        "image": "data:image/svg+xml;charset=utf-8,%3Csvg xmlns%3D'http%3A%2F%2Fwww.w3.org%2F2000%2Fsvg' viewBox%3D'0 0 300 300'%2F%3E",
        "quantity": "35g",
        "domain_url": "https://online.mmvietnam.com/"
    },
    {
        "name": "Bánh Tortilla chiên Casino",
        "price": "66,000",
        "unit": "Gói",
        "url": "https://online.mmvietnam.com/san-pham/mm-an-phu/banh-tortilla-chien-casino-150g-470935/",
        "category": "banh keo cac loai",
        "image": "data:image/svg+xml;charset=utf-8,%3Csvg xmlns%3D'http%3A%2F%2Fwww.w3.org%2F2000%2Fsvg' viewBox%3D'0 0 300 300'%2F%3E",
        "quantity": "150g",
        "domain_url": "https://online.mmvietnam.com/"
    },
    {
        "name": "Bánh Tartlet Casino mâm xôi dâu",
        "price": "109,000",
        "unit": "Hộp",
        "url": "https://online.mmvietnam.com/san-pham/mm-an-phu/banh-tartlet-casino-vi-dau-150g-470956/",
        "category": "banh keo cac loai",
        "image": "data:image/svg+xml;charset=utf-8,%3Csvg xmlns%3D'http%3A%2F%2Fwww.w3.org%2F2000%2Fsvg' viewBox%3D'0 0 300 300'%2F%3E",
        "quantity": "150g",
        "domain_url": "https://online.mmvietnam.com/"
    },
    {
        "name": "Mứt hạt dẻ cacao không béo Casino",
        "price": "149,000",
        "unit": "Chai",
        "url": "https://online.mmvietnam.com/san-pham/mm-an-phu/mut-hat-de-cacao-khong-beo-casino-300g-470431/",
        "category": "banh keo cac loai",
        "image": "data:image/svg+xml;charset=utf-8,%3Csvg xmlns%3D'http%3A%2F%2Fwww.w3.org%2F2000%2Fsvg' viewBox%3D'0 0 300 300'%2F%3E",
        "quantity": "300g",
        "domain_url": "https://online.mmvietnam.com/"
    }
]