[
    {
        "name": "Nước táo lên men Strongbow Gold",
        "price": "105,000",
        "unit": "Lốc",
        "url": "https://online.mmvietnam.com/san-pham/mm-an-phu/nuoc-tao-len-men-strongbow-gold-loc-6-lon-330ml-935239/",
        "category": "do uong cac loai",
        "image": "https://storage.googleapis.com/mm-online-bucket/ecommerce-website/uploads/media/429612-300x300.jpg",
        "quantity": "lốc 6 lon",
        "domain_url": "https://online.mmvietnam.com/"
    },
    {
        "name": "Vang đỏ Veritas + ly",
        "price": "319,000",
        "unit": "Hộp",
        "url": "https://online.mmvietnam.com/san-pham/mm-an-phu/vang-do-veritas-75cl2-ly-935261/",
        "category": "do uong cac loai",
        "image": "https://storage.googleapis.com/mm-online-bucket/ecommerce-website/uploads/media/409091-300x300.jpg",
        "quantity": "hộp 2 chai",
        "domain_url": "https://online.mmvietnam.com/"
    },
    {
        "name": "Rượu Viesta Cab Sau + kệ",
        "price": "669,000",
        "unit": "Chai",
        "url": "https://online.mmvietnam.com/san-pham/mm-an-phu/ruou-viesta-cab-sau-3-lit-ke-935280/",
        "category": "do uong cac loai",
        "image": "data:image/svg+xml;charset=utf-8,%3Csvg xmlns%3D'http%3A%2F%2Fwww.w3.org%2F2000%2Fsvg' viewBox%3D'0 0 300 300'%2F%3E",
        "quantity": "3 lít",
        "domain_url": "https://online.mmvietnam.com/"
    },
    {
        "name": "Rượu Viesta Cab Sau + kệ thuyền",
        "price": "559,000",
        "unit": "Chai",
        "url": "https://online.mmvietnam.com/san-pham/mm-an-phu/ruou-viesta-cab-sau-1-5-lit-ke-thuyen-935314/",
        "category": "do uong cac loai",
        "image": "data:image/svg+xml;charset=utf-8,%3Csvg xmlns%3D'http%3A%2F%2Fwww.w3.org%2F2000%2Fsvg' viewBox%3D'0 0 300 300'%2F%3E",
        "quantity": "1.5 lít",
        "domain_url": "https://online.mmvietnam.com/"
    },
    {
        "name": "Cà phê Wake Up sữa đá",
        "price": "35,000",
        "unit": "Hộp",
        "url": "https://online.mmvietnam.com/san-pham/mm-an-phu/ca-phe-wake-up-sua-da-hop-10-goi-24g-935547/",
        "category": "do uong cac loai",
        "image": "data:image/svg+xml;charset=utf-8,%3Csvg xmlns%3D'http%3A%2F%2Fwww.w3.org%2F2000%2Fsvg' viewBox%3D'0 0 300 300'%2F%3E",
        "quantity": "10 gói",
        "domain_url": "https://online.mmvietnam.com/"
    },
    {
        "name": "Trà hòa tan MM hương đào",
        "price": "28,500",
        "unit": "Hộp",
        "url": "https://online.mmvietnam.com/san-pham/mm-an-phu/tra-hoa-tan-mm-huong-dao-hop-16-goi-14g-927911/",
        "category": "do uong cac loai",
        "image": "data:image/svg+xml;charset=utf-8,%3Csvg xmlns%3D'http%3A%2F%2Fwww.w3.org%2F2000%2Fsvg' viewBox%3D'0 0 300 300'%2F%3E",
        "quantity": "hộp 16 gói",
        "domain_url": "https://online.mmvietnam.com/"
    },
    {
        "name": "Trà hoa hồng cân ký",
        "price": "943,000",
        "unit": "Ký",
        "url": "https://online.mmvietnam.com/san-pham/mm-an-phu/tra-hoa-hong-can-ky-cm7-927886/",
        "category": "do uong cac loai",
        "image": "data:image/svg+xml;charset=utf-8,%3Csvg xmlns%3D'http%3A%2F%2Fwww.w3.org%2F2000%2Fsvg' viewBox%3D'0 0 300 300'%2F%3E",
        "quantity": "hộp 16 gói",
        "domain_url": "https://online.mmvietnam.com/"
    },
    {
        "name": "Trà hòa tan MM hương chanh",
        "price": "28,500",
        "unit": "Hộp",
        "url": "https://online.mmvietnam.com/san-pham/mm-an-phu/tra-hoa-tan-mm-huong-chanh-hop-16-goi-14g-927903/",
        "category": "do uong cac loai",
        "image": "data:image/svg+xml;charset=utf-8,%3Csvg xmlns%3D'http%3A%2F%2Fwww.w3.org%2F2000%2Fsvg' viewBox%3D'0 0 300 300'%2F%3E",
        "quantity": "hộp 16 gói",
        "domain_url": "https://online.mmvietnam.com/"
    },
    {
        "name": "Bộ sản phẩm Special Passion Cabernet Sauvignon 75CL*2 + Hộp gỗ",
        "price": "436,000",
        "unit": "Bộ",
        "url": "https://online.mmvietnam.com/san-pham/mm-an-phu/bo-san-pham-special-passion-cabernet-sauvignon-75cl2-hop-go-925935/",
        "category": "do uong cac loai",
        "image": "data:image/svg+xml;charset=utf-8,%3Csvg xmlns%3D'http%3A%2F%2Fwww.w3.org%2F2000%2Fsvg' viewBox%3D'0 0 300 300'%2F%3E",
        "quantity": "hộp 16 gói",
        "domain_url": "https://online.mmvietnam.com/"
    },
    {
        "name": "Bộ sản phẩm Veritas Cabsau",
        "price": "649,000",
        "unit": "Bộ",
        "url": "https://online.mmvietnam.com/san-pham/mm-an-phu/bo-san-pham-veritas-cabsau-1-5-lit-ke-925951/",
        "category": "do uong cac loai",
        "image": "data:image/svg+xml;charset=utf-8,%3Csvg xmlns%3D'http%3A%2F%2Fwww.w3.org%2F2000%2Fsvg' viewBox%3D'0 0 300 300'%2F%3E",
        "quantity": "1.5 lít + kệ",
        "domain_url": "https://online.mmvietnam.com/"
    },
    {
        "name": "Chill Cocktail Light Mix",
        "price": "99,000",
        "unit": "Thùng",
        "url": "https://online.mmvietnam.com/san-pham/mm-an-phu/chill-cocktail-light-mix-6-lon-926344/",
        "category": "do uong cac loai",
        "image": "data:image/svg+xml;charset=utf-8,%3Csvg xmlns%3D'http%3A%2F%2Fwww.w3.org%2F2000%2Fsvg' viewBox%3D'0 0 300 300'%2F%3E",
        "quantity": "lốc 6 lon",
        "domain_url": "https://online.mmvietnam.com/"
    },
    {
        "name": "Cúc chi cân ký",
        "price": "1,200,000",
        "unit": "Ký",
        "url": "https://online.mmvietnam.com/san-pham/mm-an-phu/cuc-chi-can-ky-926363/",
        "category": "do uong cac loai",
        "image": "data:image/svg+xml;charset=utf-8,%3Csvg xmlns%3D'http%3A%2F%2Fwww.w3.org%2F2000%2Fsvg' viewBox%3D'0 0 300 300'%2F%3E",
        "quantity": "lốc 6 lon",
        "domain_url": "https://online.mmvietnam.com/"
    }
]