[
    {
        "name": "Asian Beef with Snow Peas",
        "cook_time": "PT10M",
        "prep_time": "PT5M",
        "total_time": "PT15M",
        "nutrition": {
            "calories": "203 kcal",
            "carbohydrateContent": "10 g",
            "cholesterolContent": "39 mg",
            "fiberContent": "2 g",
            "proteinContent": "16 g",
            "saturatedFatContent": "3 g",
            "sodiumContent": "711 mg",
            "sugarContent": "6 g",
            "fatContent": "10 g",
            "unsaturatedFatContent": "0 g"
        },
        "description": "Stir-fried beef with snow peas in a light gingery sauce.",
        "cuisine": "chinese",
        "category": "Dinner",
        "ingredient": [
            {
                "quantity": "3",
                "unit": "tablespoons",
                "name": "soy sauce"
            },
            {
                "quantity": "2",
                "unit": "tablespoons",
                "name": "rice wine"
            },
            {
                "quantity": "1",
                "unit": "tablespoon",
                "name": "brown sugar"
            },
            {
                "quantity": "½",
                "unit": "teaspoon",
                "name": "cornstarch"
            },
            {
                "quantity": "1",
                "unit": "tablespoon",
                "name": "vegetable oil"
            },
            {
                "quantity": "1",
                "unit": "tablespoon",
                "name": "minced fresh ginger root"
            },
            {
                "quantity": "1",
                "unit": "tablespoon",
                "name": "minced garlic"
            },
            {
                "quantity": "1",
                "unit": "pound",
                "name": "beef round steak, cut into thin strips"
            },
            {
                "quantity": "8",
                "unit": "ounces",
                "name": "snow peas"
            }
        ],
        "instructions": [
            {
                "text": "In a small bowl, combine the soy sauce, rice wine, brown sugar and cornstarch. Set aside."
            },
            {
                "text": "Heat oil in a wok or skillet over medium high heat. Stir-fry ginger and garlic for 30 seconds. Add the steak and stir-fry for 2 minutes or until evenly browned. Add the snow peas and stir-fry for an additional 3 minutes. Add the soy sauce mixture, bring to a boil, stirring constantly. Lower heat and simmer until the sauce is thick and smooth. Serve immediately."
            }
        ],
        "image": "https://www.allrecipes.com/thmb/vusd2voL3SdbD1AQSg2Un-Z6t7w=/1500x0/filters:no_upscale():max_bytes(150000):strip_icc()/4538031-8f8e44c458ad47eab0e7b3af58e4c5f6.jpg",
        "video": {
            "contentUrl": "https://content.jwplatform.com/videos/XYMMJ9I3-K3AjnAEN.mp4",
            "description": "For a fast weeknight dinner that’s hearty and full of flavor, you’ll love this awesome stir-fry dish. Simply make a sauce of soy sauce, rice wine, brown sugar and cornstarch. Get your wok hot, then stir-fry fresh ginger and garlic. Add a pound of beef round steak that you’ve cut into strips, and when browned, add snow peas and sauce, stirring until thick and rich. Serve over rice and enjoy! ",
            "duration": "PT47S",
            "name": "Asian Beef and Snow Peas"
        },
        "url": "https://www.allrecipes.com/recipe/15679/asian-beef-with-snow-peas/"
    },
    {
        "name": "Grilled Hoisin Beef",
        "cook_time": "PT8M",
        "prep_time": "PT10M",
        "total_time": "PT138M",
        "nutrition": {
            "calories": "404 kcal",
            "carbohydrateContent": "33 g",
            "cholesterolContent": "52 mg",
            "fiberContent": "2 g",
            "proteinContent": "30 g",
            "saturatedFatContent": "5 g",
            "sodiumContent": "2483 mg",
            "sugarContent": "22 g",
            "fatContent": "16 g",
            "unsaturatedFatContent": "0 g"
        },
        "description": "Skirt steak is marinated in a Chinese-inspired marinade with hoisin sauce and grills up in just minutes for Chef John&#39;s juicy and tender grilled hoisin beef.",
        "cuisine": "chinese",
        "category": "Dinner",
        "ingredient": [
            {
                "quantity": "1",
                "unit": "(1 pound)",
                "name": "beef skirt steak"
            },
            {
                "quantity": "⅓",
                "unit": "cup",
                "name": "hoisin sauce"
            },
            {
                "quantity": "3",
                "unit": "tablespoons",
                "name": "Chinese vinegar (or sherry vinegar)"
            },
            {
                "quantity": "1",
                "unit": "tablespoon",
                "name": "soy sauce"
            },
            {
                "quantity": "2",
                "unit": "teaspoons",
                "name": "hot sauce"
            },
            {
                "quantity": "2",
                "unit": "teaspoons",
                "name": "sesame oil"
            },
            {
                "quantity": "1",
                "unit": "tablespoon",
                "name": "grated fresh ginger root"
            },
            {
                "quantity": "4",
                "unit": "cloves",
                "name": "garlic, finely minced"
            },
            {
                "quantity": "1",
                "unit": "tablespoon",
                "name": "packed brown sugar"
            },
            {
                "quantity": "1",
                "unit": "teaspoon",
                "name": "salt"
            },
            {
                "quantity": "½",
                "unit": "teaspoon",
                "name": "freshly ground black pepper"
            },
            {
                "quantity": "1",
                "unit": null,
                "name": "green onion, light parts only, minced"
            },
            {
                "quantity": null,
                "unit": null,
                "name": "Toasted sesame seeds"
            }
        ],
        "instructions": [
            {
                "text": "Whisk hoisin sauce, vinegar, soy sauce, hot sauce, sesame oil, grated ginger, garlic, brown sugar, salt, and pepper together in a large mixing bowl."
            },
            {
                "text": "Cut skirt steak crosswise into about 4 or 5 smaller pieces. Transfer steak into marinade and toss until all pieces are evenly coated. Cover with plastic wrap. Refrigerate; marinate at least 2 hours and up to 12 hours."
            },
            {
                "text": "Line a baking pan with paper towels. Transfer pieces of steak to the paper towels and mop off some of the marinade."
            },
            {
                "text": "Preheat an outdoor grill for high heat and lightly oil the grate."
            },
            {
                "text": "Transfer steak pieces to grill. Cook to medium rare or medium, 4 to 5 minutes per side. An instant-read thermometer inserted into the center should read between 130 and 135 degrees F (about 54 degrees C). Thinner pieces might finish earlier. Transfer steak to a warm plate. Let rest for a few minutes."
            },
            {
                "text": "Transfer steak to a warm serving platter and pour any accumulated juices over skirt steak. Sprinkle with sesame seeds and sliced green onions."
            }
        ],
        "image": "https://www.allrecipes.com/thmb/YfWeTfVnkVkbxdhvDYauDkmoKic=/1500x0/filters:no_upscale():max_bytes(150000):strip_icc()/4517196-grilled-hoisin-beef-Chef-John-1x1-1-93e5ea704bed4c468887475367bdf77f.jpg",
        "video": {
            "contentUrl": "https://content.jwplatform.com/videos/9zaChMWF-K3AjnAEN.mp4",
            "description": "Create a marinade with hoisin sauce, then add vinegar, soy sauce, hot sauce, sesame oil, fresh ginger root and garlic. Add brown sugar, salt and black pepper. Cut your skirt steak into pieces and toss in the marinade to coat. When you’re ready, grill over high heat. Garnish with sesame seeds and green onions. Packed full of flavor and possibly the juiciest beef you’ll ever see or eat, be sure to add this to your summer grilling lineup for happy grilling times!",
            "duration": "PT7M3S",
            "name": "Grilled Hoisin Beef"
        },
        "url": "https://www.allrecipes.com/recipe/258215/grilled-hoisin-beef/"
    },
    {
        "name": "Black Pepper Beef and Cabbage Stir Fry",
        "cook_time": "PT15M",
        "prep_time": "PT15M",
        "total_time": "PT30M",
        "nutrition": {
            "calories": "280 kcal",
            "carbohydrateContent": "10 g",
            "cholesterolContent": "48 mg",
            "fiberContent": "3 g",
            "proteinContent": "12 g",
            "saturatedFatContent": "7 g",
            "sodiumContent": "547 mg",
            "sugarContent": "4 g",
            "fatContent": "22 g",
            "unsaturatedFatContent": "0 g"
        },
        "description": "A very simple Chinese stir-fry dish which is fabulous in taste. I saw my husband going for two additional servings of it and I had to remind him to leave some for the rest of the family! Serve with hot steamed rice.",
        "cuisine": "chinese",
        "category": "Dinner",
        "ingredient": [
            {
                "quantity": "2",
                "unit": "tablespoons",
                "name": "vegetable oil"
            },
            {
                "quantity": "4",
                "unit": "cloves",
                "name": "garlic, chopped"
            },
            {
                "quantity": "½",
                "unit": "pound",
                "name": "ground beef"
            },
            {
                "quantity": "½",
                "unit": "small head",
                "name": "cabbage, shredded"
            },
            {
                "quantity": "1",
                "unit": null,
                "name": "red bell pepper, cut into strips"
            },
            {
                "quantity": "2",
                "unit": "tablespoons",
                "name": "soy sauce"
            },
            {
                "quantity": "1",
                "unit": "teaspoon",
                "name": "cornstarch"
            },
            {
                "quantity": "½",
                "unit": "cup",
                "name": "cold water"
            },
            {
                "quantity": "1",
                "unit": "teaspoon",
                "name": "ground black pepper, or to taste"
            },
            {
                "quantity": "1",
                "unit": "pinch",
                "name": "salt, to taste"
            }
        ],
        "instructions": [
            {
                "text": "Gather ingredients."
            },
            {
                "text": "Heat a wok or large skillet over medium-high heat, and add oil. Saute garlic for about 5 seconds, then add ground beef. Stir-fry until beef is evenly brown, 5 to 7 minutes; drain excess fat."
            },
            {
                "text": "Stir in cabbage and pepper, and cook until vegetables are tender and beef is fully cooked. Stir in soy sauce."
            },
            {
                "text": "Mix together cornstarch and water, and stir in. Season with pepper; add salt to taste. Cook, stirring, until sauce has thickened."
            },
            {
                "text": "Serve hot and enjoy!"
            }
        ],
        "image": "https://www.allrecipes.com/thmb/YT9UaFlgqV4Gptx57ulT3UBZeME=/1500x0/filters:no_upscale():max_bytes(150000):strip_icc()/50233-BlackPepperBeefandCabbageStirFry-ddmps-104047-cef2008e035d4cd183cc6ad2c9abbb74.jpg",
        "video": {
            "contentUrl": "https://content.jwplatform.com/videos/lOAjxL8r-ma1DlVvV.mp4",
            "description": "Cabbage, red bell pepper, and beef combine beautifully alongside soy sauce and garlic for a simple, but flavorful dish. Add salt and pepper to taste and continue cooking until sauce has thickened. Serve over a bed of rice and add other spices if you like it spicier!",
            "duration": "PT1M15S",
            "name": "Black Pepper Beef and Cabbage Stir Fry"
        },
        "url": "https://www.allrecipes.com/recipe/50233/black-pepper-beef-and-cabbage-stir-fry/"
    },
    {
        "name": "Super-Simple, Super-Spicy Mongolian Beef",
        "cook_time": "PT10M",
        "prep_time": "PT15M",
        "total_time": "PT85M",
        "nutrition": {
            "calories": "200 kcal",
            "carbohydrateContent": "8 g",
            "cholesterolContent": "25 mg",
            "fiberContent": "1 g",
            "proteinContent": "15 g",
            "saturatedFatContent": "3 g",
            "sodiumContent": "996 mg",
            "sugarContent": "4 g",
            "fatContent": "12 g",
            "unsaturatedFatContent": "0 g"
        },
        "description": "This spicy Mongolian beef is marinated with soy, hoisin, sesame, sugar, garlic, and chili, then quickly stir-fried with green onions for a tasty dish.",
        "cuisine": "chinese",
        "category": "Dinner",
        "ingredient": [
            {
                "quantity": "¼",
                "unit": "cup",
                "name": "soy sauce"
            },
            {
                "quantity": "1",
                "unit": "tablespoon",
                "name": "hoisin sauce"
            },
            {
                "quantity": "1",
                "unit": "tablespoon",
                "name": "sesame oil"
            },
            {
                "quantity": "2",
                "unit": "teaspoons",
                "name": "white sugar"
            },
            {
                "quantity": "1",
                "unit": "tablespoon",
                "name": "minced garlic"
            },
            {
                "quantity": "1",
                "unit": "tablespoon",
                "name": "red pepper flakes (Optional)"
            },
            {
                "quantity": "1",
                "unit": "pound",
                "name": "beef flank steak, thinly sliced"
            },
            {
                "quantity": "1",
                "unit": "tablespoon",
                "name": "peanut oil"
            },
            {
                "quantity": "2",
                "unit": "large",
                "name": "green onions, thinly sliced"
            }
        ],
        "instructions": [
            {
                "text": "Whisk together soy sauce, hoisin sauce, sesame oil, sugar, garlic, and red pepper flakes in a large bowl. Toss beef with marinade; cover the bowl and refrigerate for 1 hour to overnight."
            },
            {
                "text": "Heat peanut oil in a wok or large, nonstick skillet over high heat. Cook and stir green onions in hot oil for 5 to 10 seconds. Remove beef from marinade and add to green onions in the wok; discard marinade. Cook and stir until beef is no longer pink and begins to brown, about 5 minutes."
            }
        ],
        "image": "https://www.allrecipes.com/thmb/OPRTlH-cDntVlWw-4ThIZ_vkmTo=/1500x0/filters:no_upscale():max_bytes(150000):strip_icc()/385999-9ee53db2a875481bbf4257a0ff0c2a98.jpg",
        "video": {
            "contentUrl": "https://content.jwplatform.com/videos/nwZ5TzS2-K3AjnAEN.mp4",
            "description": "As its name suggests, this easy recipe for Mongolian beef is super simple and super spicy. It makes for the perfect make-ahead dinner and only takes minutes to cook. Serve with rice and veggies on the side for a delicious weeknight meal.",
            "duration": "PT1M20S",
            "name": "How to Make Super-Simple, Super-Spicy Mongolian Beef"
        },
        "url": "https://www.allrecipes.com/recipe/148831/super-simple-super-spicy-mongolian-beef/"
    },
    {
        "name": "Chinese Pepper Steak",
        "cook_time": "PT15M",
        "prep_time": "PT15M",
        "total_time": "PT30M",
        "nutrition": {
            "calories": "312 kcal",
            "carbohydrateContent": "17 g",
            "cholesterolContent": "69 mg",
            "fiberContent": "2 g",
            "proteinContent": "26 g",
            "saturatedFatContent": "3 g",
            "sodiumContent": "972 mg",
            "sugarContent": "10 g",
            "fatContent": "15 g",
            "unsaturatedFatContent": "0 g"
        },
        "description": "This easy and delicious pepper steak recipe combines top sirloin beef with a sweet-and-savory soy sauce marinade, green pepper, onion, and tomatoes.",
        "cuisine": "chinese",
        "category": "Dinner",
        "ingredient": [
            {
                "quantity": "1",
                "unit": "pound",
                "name": "beef top sirloin steak"
            },
            {
                "quantity": "¼",
                "unit": "cup",
                "name": "soy sauce"
            },
            {
                "quantity": "2",
                "unit": "tablespoons",
                "name": "white sugar"
            },
            {
                "quantity": "2",
                "unit": "tablespoons",
                "name": "cornstarch"
            },
            {
                "quantity": "½",
                "unit": "teaspoon",
                "name": "ground ginger"
            },
            {
                "quantity": "3",
                "unit": "tablespoons",
                "name": "vegetable oil, divided"
            },
            {
                "quantity": "1",
                "unit": null,
                "name": "red onion, cut into 1-inch squares"
            },
            {
                "quantity": "1",
                "unit": null,
                "name": "green bell pepper, cut into 1-inch squares"
            },
            {
                "quantity": "2",
                "unit": null,
                "name": "tomatoes, cut into wedges"
            }
        ],
        "instructions": [
            {
                "text": "Slice steak into 1/2-inch thick slices across the grain."
            },
            {
                "text": "Whisk together soy sauce, sugar, cornstarch, and ginger in a bowl until the sugar has dissolved and the mixture is smooth. Place steak slices into the marinade, and stir until well-coated."
            },
            {
                "text": "Heat 1 tablespoon vegetable oil in a wok or large skillet over medium-high heat, and cook steak strips in batches in hot oil so as not to crowd the pan. Cook and stir until well-browned, about 3 minutes, and remove steak from the wok to a bowl. Repeat with remaining steak, adding more oil as needed, and set the cooked meat aside."
            },
            {
                "text": "Return cooked steak strips to the hot wok, and stir in onion. Toss steak and onion together until onion begins to soften, about 2 minutes, then stir in green pepper."
            },
            {
                "text": "Cook and stir the mixture until peppers have turned bright green and started to become tender, about 2 minutes more, then add tomatoes."
            },
            {
                "text": "Stir everything together to mix and blend flavors, and serve."
            }
        ],
        "image": "https://www.allrecipes.com/thmb/nNbgtTe12-A9YS9Ox4D_IhmmSCQ=/1500x0/filters:no_upscale():max_bytes(150000):strip_icc()/172704-chinese-pepper-steak-DDMFS-4x3-5e58e36f7885463799f1267671c8f066.jpg",
        "video": {
            "contentUrl": "https://content.jwplatform.com/videos/h3FmaRuo-K3AjnAEN.mp4",
            "description": "Watch how to take a piece of steak and turn it into a sweet-and-savory stir fry dish with vegetables. The secret is to cut the steak against the grain and quickly marinate it in soy sauce with sugar, cornstarch and ginger. Stir in the vegetables, and dinner is ready in just half an hour.",
            "duration": "PT2M3S",
            "name": "Chinese Pepper Steak"
        },
        "url": "https://www.allrecipes.com/recipe/172704/chinese-pepper-steak/"
    },
    {
        "name": "Mongolian Beef and Spring Onions",
        "cook_time": "PT10M",
        "prep_time": "PT15M",
        "total_time": "PT35M",
        "nutrition": {
            "calories": "391 kcal",
            "carbohydrateContent": "55 g",
            "cholesterolContent": "27 mg",
            "fiberContent": "3 g",
            "proteinContent": "18 g",
            "saturatedFatContent": "3 g",
            "sodiumContent": "1862 mg",
            "sugarContent": "39 g",
            "fatContent": "12 g",
            "unsaturatedFatContent": "0 g"
        },
        "description": "This Mongolian beef recipe features crispy slices of flank steak with a sweet soy-based sauce and green onions for a restaurant-quality dish at home!",
        "cuisine": "chinese",
        "category": "Dinner",
        "ingredient": [
            {
                "quantity": "2",
                "unit": "teaspoons",
                "name": "vegetable oil"
            },
            {
                "quantity": "1",
                "unit": "tablespoon",
                "name": "finely chopped garlic"
            },
            {
                "quantity": "½",
                "unit": "teaspoon",
                "name": "grated fresh ginger root"
            },
            {
                "quantity": "⅔",
                "unit": "cup",
                "name": "dark brown sugar"
            },
            {
                "quantity": "½",
                "unit": "cup",
                "name": "soy sauce"
            },
            {
                "quantity": "½",
                "unit": "cup",
                "name": "water"
            },
            {
                "quantity": "1",
                "unit": "pound",
                "name": "beef flank steak, sliced 1/4 inch thick on the diagonal"
            },
            {
                "quantity": "¼",
                "unit": "cup",
                "name": "cornstarch"
            },
            {
                "quantity": "1",
                "unit": "cup",
                "name": "vegetable oil for frying"
            },
            {
                "quantity": "2",
                "unit": "bunches",
                "name": "green onions, cut in 2-inch lengths"
            }
        ],
        "instructions": [
            {
                "text": "Heat 2 teaspoons of vegetable oil in a saucepan over medium heat. Add garlic and ginger; cook and stir until fragrant, about 30 seconds. Stir in brown sugar, soy sauce, and water. Increase heat to medium-high; stir until sauce boils and slightly thickens, about 4 minutes. Remove sauce from the heat and set aside."
            },
            {
                "text": "Place beef into a large bowl; add cornstarch and mix until beef is thoroughly coated. Set aside until most of the cornstarch has been absorbed, about 10 minutes."
            },
            {
                "text": "Heat vegetable oil in a deep skillet to 375 degrees F (190 degrees C)."
            },
            {
                "text": "Shake excess cornstarch from beef slices and drop into hot oil, a few at a time, stirring briefly and frying until edges become crisp, about 2 minutes. Remove beef with a large slotted spoon; drain on paper towels."
            },
            {
                "text": "Remove excess oil from the skillet, then heat the skillet over medium heat; add beef slices and stir in prepared sauce. Add green onions and bring to a boil; cook until the onions have just softened and are bright green, about 1 to 2 minutes."
            }
        ],
        "image": "https://www.allrecipes.com/thmb/o7avKwxRRBLQCg16DdAefG8LmBo=/1500x0/filters:no_upscale():max_bytes(150000):strip_icc()/9083831-mongolian-beef-and-spring-onions-Megan-Nieves-1x1-1-feb41bcec3ca452c84c3c35cfe900a51.jpg",
        "video": {
            "contentUrl": "https://content.jwplatform.com/videos/s1l7Pmgq-K3AjnAEN.mp4",
            "description": "Spicy, sweet, and savory beef can do no wrong for a dinner meal! It’s everything you want, full of flavor and tender meat. \n",
            "duration": "PT1M",
            "name": "Mongolian Beef and Spring Onions "
        },
        "url": "https://www.allrecipes.com/recipe/201849/mongolian-beef-and-spring-onions/"
    },
    {
        "name": "Quick Beef Stir-Fry",
        "cook_time": "PT10M",
        "prep_time": "PT15M",
        "total_time": "PT25M",
        "nutrition": {
            "calories": "268 kcal",
            "carbohydrateContent": "9 g",
            "cholesterolContent": "49 mg",
            "fiberContent": "3 g",
            "proteinContent": "23 g",
            "saturatedFatContent": "4 g",
            "sodiumContent": "526 mg",
            "sugarContent": "3 g",
            "fatContent": "16 g",
            "unsaturatedFatContent": "0 g"
        },
        "description": "This beef stir-fry is quick and easy for busy weeknights. Thin slices of beef sirloin are stir-fried with colorful vegetables and soy sauce.",
        "cuisine": "chinese",
        "category": "Dinner",
        "ingredient": [
            {
                "quantity": "2",
                "unit": "tablespoons",
                "name": "vegetable oil"
            },
            {
                "quantity": "1",
                "unit": "pound",
                "name": "beef sirloin, cut into 2-inch strips"
            },
            {
                "quantity": "1 ½",
                "unit": "cups",
                "name": "fresh broccoli florets"
            },
            {
                "quantity": "1",
                "unit": null,
                "name": "red bell pepper, cut into matchsticks"
            },
            {
                "quantity": "2",
                "unit": null,
                "name": "carrots, thinly sliced"
            },
            {
                "quantity": "1",
                "unit": null,
                "name": "green onion, chopped"
            },
            {
                "quantity": "1",
                "unit": "teaspoon",
                "name": "minced garlic"
            },
            {
                "quantity": "2",
                "unit": "tablespoons",
                "name": "soy sauce"
            },
            {
                "quantity": "2",
                "unit": "tablespoons",
                "name": "sesame seeds, toasted"
            }
        ],
        "instructions": [
            {
                "text": "Gather all ingredients."
            },
            {
                "text": "Heat vegetable oil in a large wok or skillet over medium-high heat; cook and stir beef until browned, 3 to 4 minutes."
            },
            {
                "text": "Move beef to the side of the wok and add broccoli, bell pepper, carrots, green onion, and garlic to the center of the wok. Cook and stir vegetables for 2 minutes."
            },
            {
                "text": "Stir beef into vegetables and season with soy sauce and sesame seeds. Continue to cook and stir until vegetables are tender, about 2 more minutes."
            },
            {
                "text": "Serve hot and enjoy!"
            }
        ],
        "image": "https://www.allrecipes.com/thmb/7N-Xq1XMMJw8G0KJv2e0ETUYB2I=/1500x0/filters:no_upscale():max_bytes(150000):strip_icc()/228823-quick-beef-stir-fry-DDMFS-4x3-1f79b031d3134f02ac27d79e967dfef5.jpg",
        "video": {
            "contentUrl": "https://content.jwplatform.com/videos/42HrKYPC-K3AjnAEN.mp4",
            "description": "Need to use up some of your leftover vegetables and pantry staple ingredients? Look no further than this quick beef stir-fry recipe. This video shows you how to make beef stir-fry with veggies like broccoli, bell pepper, carrots, and green onion. (Customize as you’d like with the vegetables you have on hand!) The top-rated stir-fry comes together in just 25 minutes, which makes it the perfect dinner recipe to make on busy weeknights.",
            "duration": "PT57S",
            "name": "Quick Beef Stir-Fry Recipe"
        },
        "url": "https://www.allrecipes.com/recipe/228823/quick-beef-stir-fry/"
    }
]